lunchbox/__init__.py
lunchbox/command.py
lunchbox/enforce.py
lunchbox/py.typed
lunchbox/singleton.py
lunchbox/stopwatch.py
lunchbox/theme.py
lunchbox/tools.py
lunchbox-0.6.2.dist-info/entry_points.txt
lunchbox-0.6.2.dist-info/WHEEL
lunchbox-0.6.2.dist-info/METADATA
lunchbox-0.6.2.dist-info/licenses/LICENSE
lunchbox-0.6.2.dist-info/RECORD
