Metadata-Version: 2.1
Name: lunchbox
Version: 0.6.2
Summary: A library of various tools for common python tasks
License: MIT
Keywords: tool,tools,general,slack,enforce
Author-email: Alex Braun <alexander.g.braun@gmail.com>
Requires-Python: >=3.10
Classifier: Development Status :: 4 - Beta
Classifier: Intended Audience :: Developers
Classifier: License :: OSI Approved :: MIT License
Classifier: Programming Language :: Python :: 3
Classifier: Programming Language :: Python :: 3.10
Classifier: Programming Language :: Python :: 3.11
Classifier: Programming Language :: Python :: 3.12
Classifier: Programming Language :: Python :: 3.13
Classifier: Typing :: Typed
Requires-Dist: click>=8.1.3
Requires-Dist: humanfriendly
Requires-Dist: wrapt
Project-URL: documentation, https://theNewFlesh.github.io/lunchbox
Project-URL: repository, https://github.com/thenewflesh/lunchbox
